inline/__about__.py
inline/__init__.py
inline/ast_future.py
inline/inline.py
inline/plugin.py
pytest_inline-1.1.0.dist-info/METADATA
pytest_inline-1.1.0.dist-info/WHEEL
pytest_inline-1.1.0.dist-info/entry_points.txt
pytest_inline-1.1.0.dist-info/licenses/LICENSE
pytest_inline-1.1.0.dist-info/RECORD
