Metadata-Version: 2.3
Name: pytest-inline
Version: 1.1.0
Summary: A pytest plugin for writing inline tests
Project-URL: Issues, https://github.com/pytest-dev/pytest-inline/issues
Project-URL: Source, https://github.com/pytest-dev/pytest-inline
Author-email: Yu Liu <im.yukiliu@gmail.com>
Maintainer-email: Yu Liu <im.yukiliu@gmail.com>, Pengyu Nie <prodigy.sov@gmail.com>, Zachary William Thurston <zwt3@cornell.edu>, Alan Han <ayh9@cornell.edu>
License: Copyright (c) 2022-present Inline Tests Dev Team
License-File: LICENSE
Classifier: Development Status :: 4 - Beta
Classifier: Framework :: Pytest
Classifier: Intended Audience :: Developers
Classifier: License :: OSI Approved :: MIT License
Classifier: Operating System :: OS Independent
Classifier: Programming Language :: Python
Classifier: Programming Language :: Python :: 3
Classifier: Programming Language :: Python :: 3 :: Only
Classifier: Programming Language :: Python :: 3.7
Classifier: Programming Language :: Python :: 3.8
Classifier: Programming Language :: Python :: 3.9
Classifier: Programming Language :: Python :: 3.10
Classifier: Programming Language :: Python :: Implementation :: CPython
Classifier: Programming Language :: Python :: Implementation :: PyPy
Classifier: Topic :: Software Development :: Testing
Requires-Python: >=3.7
Requires-Dist: pytest<9.0,>=7.0
Provides-Extra: dev
Requires-Dist: black; extra == 'dev'
Requires-Dist: coverage[toml]; extra == 'dev'
Requires-Dist: hatch; extra == 'dev'
Requires-Dist: ruff; extra == 'dev'
Requires-Dist: tox; extra == 'dev'
Requires-Dist: tox-gh; extra == 'dev'
